gitrc/__init__.py
gitrc/__main__.py
gitrc/gitrc.py
gitrc-1.0.1.dist-info/LICENSE
gitrc-1.0.1.dist-info/METADATA
gitrc-1.0.1.dist-info/WHEEL
gitrc-1.0.1.dist-info/entry_points.txt
gitrc-1.0.1.dist-info/top_level.txt
gitrc-1.0.1.dist-info/RECORD
