Metadata-Version: 2.1
Name: gitrc
Version: 1.0.1
Summary: A package to dowload all repos from Github for a given user or organization.
Author-email: Mike Ellertson <mike@cybertron.ninja>
License: MIT License
Project-URL: Homepage, https://github.com/mellertson/gitrc.git
Project-URL: Bug Tracker, https://github.com/mellertson/gitrc/issues
Classifier: Programming Language :: Python :: 3
Classifier: License :: OSI Approved :: MIT License
Classifier: Operating System :: OS Independent
Requires-Python: >=3.7
License-File: LICENSE
